Metadata-Version: 2.1
Name: tff-nightly
Version: 0.0.1.dev20231211
Summary: High-performance TensorFlow library for quantitative finance.
Home-page: https://github.com/google/tf-quant-finance
Author: Google Inc.
Author-email: tf-quant-finance@google.com
License: Apache 2.0
Keywords: tensorflow quantitative finance hpc gpu option pricing
Classifier: Development Status :: 2 - Pre-Alpha
Classifier: Intended Audience :: Developers
Classifier: Intended Audience :: Education
Classifier: Intended Audience :: Financial and Insurance Industry
Classifier: License :: OSI Approved :: Apache Software License
Classifier: Programming Language :: Python :: 3.4
Classifier: Programming Language :: Python :: 3.5
Classifier: Programming Language :: Python :: 3.6
Classifier: Programming Language :: Python :: 3.7
Classifier: Natural Language :: English
Classifier: Topic :: Scientific/Engineering :: Mathematics
Classifier: Topic :: Software Development :: Libraries :: Python Modules
Classifier: Topic :: Software Development :: Libraries
Classifier: Operating System :: OS Independent
License-File: LICENSE
Requires-Dist: attrs (>=18.2.0)
Requires-Dist: tensorflow-probability (>=0.12.1)
Requires-Dist: numpy (>=1.21)
Requires-Dist: protobuf
